LICENSE.txt
MANIFEST.in
README.rst
setup.cfg
setup.py
hep_rfm/__init__.py
hep_rfm/core.py
hep_rfm/exceptions.py
hep_rfm/fields.py
hep_rfm/files.py
hep_rfm/parallel.py
hep_rfm/protocols.py
hep_rfm/tables.py
hep_rfm/version.py
hep_rfm.egg-info/PKG-INFO
hep_rfm.egg-info/SOURCES.txt
hep_rfm.egg-info/dependency_links.txt
hep_rfm.egg-info/requires.txt
hep_rfm.egg-info/top_level.txt
scripts/hep-rfm-old-table-to-new
scripts/hep-rfm-table