Metadata-Version: 1.0
Name: hep-rfm
Version: 0.0.0.dev4
Summary: Tools to manage remote and local files using the xrootd and ssh protocols
Home-page: UNKNOWN
Author: UNKNOWN
Author-email: UNKNOWN
License: UNKNOWN
Keywords: physics hep file management
Platform: UNKNOWN
